mistercar_input_devices/__init__.py
mistercar_input_devices/backend/__init__.py
mistercar_input_devices/backend/linux/__init__.py
mistercar_input_devices/backend/linux/adapters/__init__.py
mistercar_input_devices/backend/linux/adapters/input_emulators/__init__.py
mistercar_input_devices/backend/linux/adapters/input_emulators/gamepad_emulator_adapter.py
mistercar_input_devices/backend/linux/adapters/input_emulators/keyboard_emulator_adapter.py
mistercar_input_devices/backend/linux/adapters/input_emulators/mouse_emulator_adapter.py
mistercar_input_devices/backend/linux/adapters/input_readers/__init__.py
mistercar_input_devices/backend/linux/adapters/input_readers/gamepad_reader_adapter.py
mistercar_input_devices/backend/linux/adapters/input_readers/keyboard_reader_adapter.py
mistercar_input_devices/backend/linux/adapters/input_readers/mouse_reader_adapter.py
mistercar_input_devices/backend/linux/platform_specific/__init__.py
mistercar_input_devices/backend/macos/__init__.py
mistercar_input_devices/backend/macos/adapters/__init__.py
mistercar_input_devices/backend/macos/adapters/input_emulators/__init__.py
mistercar_input_devices/backend/macos/adapters/input_emulators/gamepad_emulator_adapter.py
mistercar_input_devices/backend/macos/adapters/input_emulators/keyboard_emulator_adapter.py
mistercar_input_devices/backend/macos/adapters/input_emulators/mouse_emulator_adapter.py
mistercar_input_devices/backend/macos/adapters/input_readers/__init__.py
mistercar_input_devices/backend/macos/adapters/input_readers/gamepad_reader_adapter.py
mistercar_input_devices/backend/macos/adapters/input_readers/keyboard_reader_adapter.py
mistercar_input_devices/backend/macos/adapters/input_readers/mouse_reader_adapter.py
mistercar_input_devices/backend/macos/platform_specific/__init__.py
mistercar_input_devices/backend/multiplatform/__init__.py
mistercar_input_devices/backend/multiplatform/input_emulators/__init__.py
mistercar_input_devices-0.4.0.dist-info/licenses/LICENSE
mistercar_input_devices-0.4.0.dist-info/METADATA
mistercar_input_devices-0.4.0.dist-info/WHEEL
mistercar_input_devices-0.4.0.dist-info/RECORD
