Metadata-Version: 2.4
Name: mistercar-input-devices
Version: 0.4.0
Summary: Read and emulate keyboard, mouse, gamepad, and steering wheel
License: MIT
License-File: LICENSE
Keywords: input reading,input emulation,GUI automation,keyboard,mouse,gamepad
Author: PypayaTech
Requires-Python: >=3.10,<4.0
Classifier: Intended Audience :: Developers
Classifier: License :: OSI Approved :: MIT License
Classifier: Operating System :: OS Independent
Classifier: Programming Language :: Python :: 3
Classifier: Programming Language :: Python :: 3.10
Classifier: Programming Language :: Python :: 3.11
Classifier: Programming Language :: Python :: 3.12
Classifier: Programming Language :: Python :: 3.13
Classifier: Programming Language :: Python :: 3.14
Requires-Dist: PyAutoGUI (>=0.9.54,<0.10.0)
Requires-Dist: pywin32 (>=306,<307) ; sys_platform == "win32"
Requires-Dist: pywinusb (>=0.4.2) ; sys_platform == "win32"
Project-URL: Homepage, https://github.com/PypayaTech/mistercar-input-devices
Project-URL: Repository, https://github.com/PypayaTech/mistercar-input-devices
